autogit/__init__.py
autogit/autogit.py
autogit/commands/__init__.py
autogit/commands/checkout.py
autogit/commands/checkout_command_test.py
autogit/commands/createworkspace.py
autogit/commands/createworkspace_command_test.py
autogit/commands/name_branch_test.py
luis_autogit-0.4.0.dist-info/licenses/LICENSE
luis_autogit-0.4.0.dist-info/METADATA
luis_autogit-0.4.0.dist-info/WHEEL
luis_autogit-0.4.0.dist-info/entry_points.txt
luis_autogit-0.4.0.dist-info/top_level.txt
luis_autogit-0.4.0.dist-info/RECORD
