Metadata-Version: 2.4
Name: luis-autogit
Version: 0.4.0
Summary: Utilities to automate frequently used git workflows.
Project-URL: source, https://github.com/luistm/autogit
License-File: LICENSE
Requires-Dist: python-slugify>=8.0.0
Dynamic: license-file
